OpenDHW/OpenDHW.py
OpenDHW/__init__.py
OpenDHW/Data/__init__.py
OpenDHW/Data/prob_nonresidential.json
OpenDHW/Data/prob_residential.json
OpenDHW/utils/OpenDHW_Utilities.py
OpenDHW/utils/__init__.py
opendhw-0.2.5.dist-info/LICENSE
opendhw-0.2.5.dist-info/METADATA
opendhw-0.2.5.dist-info/WHEEL
opendhw-0.2.5.dist-info/top_level.txt
opendhw-0.2.5.dist-info/RECORD
